agilab/AGILAB.py
agilab/__init__.py
agilab/agi_codex.py
agilab/lab_run.py
agilab/steps.toml
agilab/uv_config.toml
agilab/apps-pages/README.md
agilab/apps-pages/view_autoencoder_latenspace/pyproject.toml
agilab/apps-pages/view_autoencoder_latenspace/src/view_autoencoder_latentspace/__init__.py
agilab/apps-pages/view_autoencoder_latenspace/src/view_autoencoder_latentspace/autoencoder_latentspace.py
agilab/apps-pages/view_autoencoder_latenspace/src/view_autoencoder_latentspace/view_autoencoder_latentspace.py
agilab/apps-pages/view_barycentric/__init__.py
agilab/apps-pages/view_barycentric/pyproject.toml
agilab/apps-pages/view_barycentric/src/view_barycentric/__init__.py
agilab/apps-pages/view_barycentric/src/view_barycentric/barycentric_graph.py
agilab/apps-pages/view_barycentric/src/view_barycentric/view_barycentric.py
agilab/apps-pages/view_maps/pyproject.toml
agilab/apps-pages/view_maps/src/view_maps/__init__.py
agilab/apps-pages/view_maps/src/view_maps/maps.py
agilab/apps-pages/view_maps/src/view_maps/view_maps.py
agilab/apps-pages/view_maps_3d/pyproject.toml
agilab/apps-pages/view_maps_3d/src/view_maps_3d/__init__.py
agilab/apps-pages/view_maps_3d/src/view_maps_3d/maps_3d.py
agilab/apps-pages/view_maps_3d/src/view_maps_3d/view_maps_3d.py
agilab/apps-pages/view_maps_network/pyproject.toml
agilab/apps-pages/view_maps_network/src/view_maps_network/maps_network_graph.py
agilab/apps-pages/view_maps_network/src/view_maps_network/view_maps_network.py
agilab/pages/▶️ EDIT.py
agilab/pages/▶️ EXECUTE.py
agilab/pages/▶️ EXPERIMENT.py
agilab/pages/▶️ EXPLORE.py
agilab/resources/__init__.py
agilab/resources/agi_logo.png
agilab/resources/agilab_logo.png
agilab/resources/code_editor.scss
agilab/resources/config.toml
agilab/resources/custom_buttons.json
agilab/resources/info_bar.json
agilab/resources/theme.css
agilab/resources/help/__init__.py
agilab/resources/help/cluster-help.html
agilab/resources/help/edit_help.html
agilab/resources/help/execute_help.html
agilab-2025.12.19.dist-info/licenses/LICENSE
agilab-2025.12.19.dist-info/licenses/NOTICE
agilab-2025.12.19.dist-info/METADATA
agilab-2025.12.19.dist-info/WHEEL
agilab-2025.12.19.dist-info/entry_points.txt
agilab-2025.12.19.dist-info/top_level.txt
agilab-2025.12.19.dist-info/RECORD
