Metadata-Version: 2.4
Name: agilab
Version: 2025.12.19
Summary: AGILAB is a PyCharm‑integrated AI experimentation lab for engineering (requires PyCharm for full workflow)
Author-email: Jean-Pierre Morard <focus@thalesgroup.com>
Project-URL: Documentation, https://thalesgroup.github.io/agilab
Project-URL: Source, https://github.com/ThalesGroup/agilab
Project-URL: Issues, https://github.com/ThalesGroup/agilab/issues
Keywords: jupyterai,mlflow,asyncio,dask,rapids,streamlit,distributed,cython,cluster,dataframe,dataset,loadbalancing,genai,agi,pycharm,datascience,codex,ollama
Classifier: Intended Audience :: Developers
Classifier: Development Status :: 3 - Alpha
Classifier: Programming Language :: Python :: 3
Classifier: Programming Language :: Python :: 3.11
Classifier: Programming Language :: Python :: 3.12
Classifier: Programming Language :: Python :: 3.13
Classifier: Operating System :: MacOS
Classifier: Operating System :: Microsoft :: Windows
Classifier: Operating System :: POSIX :: Linux
Requires-Python: >=3.11
License-File: LICENSE
License-File: NOTICE
Requires-Dist: astor
Requires-Dist: asyncssh
Requires-Dist: build
Requires-Dist: cmake>=3.29
Requires-Dist: fastparquet
Requires-Dist: geojson
Requires-Dist: geopy
Requires-Dist: humanize
Requires-Dist: jupyter-ai[all]
Requires-Dist: keras
Requires-Dist: matplotlib
Requires-Dist: mlflow
Requires-Dist: networkx
Requires-Dist: noise
Requires-Dist: numba
Requires-Dist: numpy>=1.14.1
Requires-Dist: openai
Requires-Dist: pathspec
Requires-Dist: pip
Requires-Dist: plotly
Requires-Dist: polars
Requires-Dist: pulp
Requires-Dist: py7zr
Requires-Dist: pytest-cov
Requires-Dist: scipy==1.15.2
Requires-Dist: seaborn
Requires-Dist: setuptools
Requires-Dist: streamlit
Requires-Dist: streamlit-modal
Requires-Dist: streamlit_code_editor
Requires-Dist: streamlit_extras
Requires-Dist: tomli
Requires-Dist: tomli_w
Requires-Dist: twine
Requires-Dist: watchdog
Requires-Dist: wheel
Requires-Dist: sgp4
Requires-Dist: agi-core==2025.12.19
Requires-Dist: legacy-cgi; python_version >= "3.13"
Requires-Dist: standard-imghdr; python_version >= "3.13"
Provides-Extra: offline
Requires-Dist: gpt-oss>=0.0.8; python_version >= "3.12" and extra == "offline"
Requires-Dist: universal-offline-ai-chatbot>=0.1.0; python_version >= "3.12" and extra == "offline"
Requires-Dist: transformers>=4.57.0; python_version >= "3.12" and extra == "offline"
Requires-Dist: torch>=2.8.0; python_version >= "3.12" and extra == "offline"
Requires-Dist: accelerate>=0.34.2; python_version >= "3.12" and extra == "offline"
Dynamic: license-file
